ai2sql/__init__.py
ai2sql/cli.py
ai2sql/core.py
ai2sql/db_manager.py
ai2sql_cli-0.1.0.dist-info/LICENSE
ai2sql_cli-0.1.0.dist-info/METADATA
ai2sql_cli-0.1.0.dist-info/WHEEL
ai2sql_cli-0.1.0.dist-info/entry_points.txt
ai2sql_cli-0.1.0.dist-info/top_level.txt
ai2sql_cli-0.1.0.dist-info/RECORD
