Metadata-Version: 2.1
Name: ai2sql-cli
Version: 0.1.0
Summary: A CLI tool for converting natural language to SQL using AI
Home-page: https://github.com/mergisi/ai2sql-cli
Author: Mustafa Ergisi
Author-email: support@ai2sql.io
Classifier: Programming Language :: Python :: 3
Classifier: License :: OSI Approved :: MIT License
Classifier: Operating System :: OS Independent
Requires-Python: >=3.7
License-File: LICENSE
Requires-Dist: openai>=1.0.0
Requires-Dist: sqlalchemy>=1.4.0
Requires-Dist: mysql-connector-python>=8.0.0
